{"119309946RR0001": {" bosniaks": false, " panjabi": false, "tibet": false, "pakistan": false, "lebanon": false, "bangla": false, "egyptian": false, " pashayi": false, "somalia": false, "egypt": false, " palestinina arabic": false, "sri lanka": false, "hindi": false, "uyghur": false, "gujarati": false, " kurdish": false, " berber": false, "hebrew": true, " chiminii": false, "turkish": false, "tunisia": false, " turkmen": false, "dari": false, " helabasa": false, "jewish": false, "afghan": false, "somali": false, "turkey": false, "lebanese": false, " serbian": false, "turk": false, " armenian": false, "punjabi": false, "bangaldeshi": false, " egyptian arabic": false, "bosnian": false, "israel": false, " lebanese arabic": false, " circassian": false, "cambodia": false, "palestinian": false, "iran": false, " arabic": false, "moroccan": false, "tibetan": false, " maay": false, " hindi": false, "arabic": false, "pakistani": false, "palestine": false, " zazaki": false, "tunisian": false, "sinhala": false, "persian": false, "algerian": false, " baraawe": false, "syrian": false, " turkiye": false, "sri lankan": false, " pashto": false, " uzbek": false, "tunisian arabic": false, "khmer": false, " tamil": false, " farsi": false, "urdu": false, " spanish": false, " french": false, "afghanistan": false, " turkish": false, " croatian": false, " tamazight": false, "syria": false, "indian hindhu": false, "bangladesh": false, " balochi": false, "algeria": false, "morocco": false, "cambodian": false, "iranian": false}, "119309995RR0001": {" bosniaks": false, " panjabi": false, "tibet": false, "pakistan": false, "lebanon": false, "bangla": false, "egyptian": false, " pashayi": false, "somalia": false, "egypt": false, " palestinina arabic": false, "sri lanka": false, "hindi": false, "uyghur": false, "gujarati": false, " kurdish": false, " berber": false, "hebrew": false, " chiminii": false, "turkish": false, "tunisia": false, " turkmen": false, "dari": false, " helabasa": false, "jewish": false, "afghan": false, "somali": false, "turkey": false, "lebanese": false, " serbian": false, "turk": false, " armenian": false, "punjabi": false, "bangaldeshi": false, " egyptian arabic": false, "bosnian": false, "israel": false, " lebanese arabic": false, " circassian": false, "cambodia": false, "palestinian": false, "iran": false, " arabic": false, "moroccan": false, "tibetan": false, " maay": false, " hindi": false, "arabic": false, "pakistani": false, "palestine": false, " zazaki": false, "tunisian": false, "sinhala": false, "persian": false, "algerian": false, " baraawe": false, "syrian": false, " turkiye": false, "sri lankan": false, " pashto": false, " uzbek": false, "tunisian arabic": false, "khmer": false, " tamil": false, " farsi": false, "urdu": false, " spanish": false, " french": false, "afghanistan": false, " turkish": false, " croatian": false, " tamazight": false, "syria": false, "indian hindhu": false, "bangladesh": false, " balochi": false, "algeria": false, "morocco": false, "cambodian": false, "iranian": false}, "705524932RR0001": {" bosniaks": false, " panjabi": false, "tibet": false, "pakistan": false, "lebanon": false, "bangla": false, "egyptian": false, " pashayi": false, "somalia": false, "egypt": false, " palestinina arabic": false, "sri lanka": false, "hindi": false, "uyghur": false, "gujarati": false, " kurdish": false, " berber": false, "hebrew": false, " chiminii": false, "turkish": false, "tunisia": false, " turkmen": false, "dari": false, " helabasa": false, "jewish": false, "afghan": false, "somali": false, "turkey": false, "lebanese": false, " serbian": false, "turk": false, " armenian": false, "punjabi": false, "bangaldeshi": false, " egyptian arabic": false, "bosnian": false, "israel": false, " lebanese arabic": false, " circassian": false, "cambodia": false, "palestinian": false, "iran": false, " arabic": false, "moroccan": false, "tibetan": false, " maay": false, " hindi": false, "arabic": false, "pakistani": false, "palestine": false, " zazaki": false, "tunisian": false, "sinhala": false, "persian": false, "algerian": false, " baraawe": false, "syrian": false, " turkiye": false, "sri lankan": false, " pashto": false, " uzbek": false, "tunisian arabic": false, "khmer": false, " tamil": false, " farsi": false, "urdu": false, " spanish": false, " french": false, "afghanistan": false, " turkish": false, " croatian": false, " tamazight": false, "syria": false, "indian hindhu": false, "bangladesh": false, " balochi": false, "algeria": false, "morocco": false, "cambodian": false, "iranian": false}, "769847120RR0001": {" bosniaks": false, " panjabi": false, "tibet": false, "pakistan": false, "lebanon": false, "bangla": false, "egyptian": false, " pashayi": false, "somalia": false, "egypt": false, " palestinina arabic": false, "sri lanka": false, "hindi": false, "uyghur": false, "gujarati": false, " kurdish": false, " berber": false, "hebrew": false, " chiminii": false, "turkish": false, "tunisia": false, " turkmen": false, "dari": false, " helabasa": false, "jewish": false, "afghan": false, "somali": false, "turkey": false, "lebanese": false, " serbian": false, "turk": false, " armenian": false, "punjabi": false, "bangaldeshi": false, " egyptian arabic": false, "bosnian": false, "israel": false, " lebanese arabic": false, " circassian": false, "cambodia": false, "palestinian": false, "iran": false, " arabic": false, "moroccan": false, "tibetan": false, " maay": false, " hindi": false, "arabic": false, "pakistani": false, "palestine": false, " zazaki": false, "tunisian": false, "sinhala": false, "persian": false, "algerian": false, " baraawe": false, "syrian": false, " turkiye": false, "sri lankan": false, " pashto": false, " uzbek": false, "tunisian arabic": false, "khmer": false, " tamil": false, " farsi": false, "urdu": false, " spanish": false, " french": false, "afghanistan": false, " turkish": false, " croatian": false, " tamazight": false, "syria": false, "indian hindhu": false, "bangladesh": false, " balochi": false, "algeria": false, "morocco": false, "cambodian": false, "iranian": false}, "744160003RR0001": {" bosniaks": false, " panjabi": false, "tibet": false, "pakistan": false, "lebanon": false, "bangla": false, "egyptian": false, " pashayi": false, "somalia": false, "egypt": false, " palestinina arabic": false, "sri lanka": false, "hindi": false, "uyghur": false, "gujarati": false, " kurdish": false, " berber": false, "hebrew": false, " chiminii": false, "turkish": false, "tunisia": false, " turkmen": false, "dari": false, " helabasa": false, "jewish": false, "afghan": false, "somali": false, "turkey": false, "lebanese": false, " serbian": false, "turk": false, " armenian": false, "punjabi": false, "bangaldeshi": false, " egyptian arabic": false, "bosnian": false, "israel": false, " lebanese arabic": false, " circassian": false, "cambodia": false, "palestinian": false, "iran": false, " arabic": false, "moroccan": false, "tibetan": false, " maay": false, " hindi": false, "arabic": false, "pakistani": false, "palestine": false, " zazaki": false, "tunisian": false, "sinhala": false, "persian": false, "algerian": false, " baraawe": false, "syrian": false, " turkiye": false, "sri lankan": false, " pashto": false, " uzbek": false, "tunisian arabic": false, "khmer": false, " tamil": false, " farsi": false, "urdu": false, " spanish": false, " french": false, "afghanistan": false, " turkish": false, " croatian": false, " tamazight": false, "syria": false, "indian hindhu": false, "bangladesh": false, " balochi": false, "algeria": false, "morocco": false, "cambodian": false, "iranian": false}, "889280103RR0001": {" bosniaks": false, " panjabi": false, "tibet": false, "pakistan": false, "lebanon": false, "bangla": false, "egyptian": false, " pashayi": false, "somalia": false, "egypt": false, " palestinina arabic": false, "sri lanka": false, "hindi": false, "uyghur": false, "gujarati": false, " kurdish": false, " berber": false, "hebrew": false, " chiminii": false, "turkish": false, "tunisia": false, " turkmen": false, "dari": false, " helabasa": false, "jewish": false, "afghan": false, "somali": false, "turkey": false, "lebanese": false, " serbian": false, "turk": false, " armenian": false, "punjabi": false, "bangaldeshi": false, " egyptian arabic": false, "bosnian": false, "israel": false, " lebanese arabic": false, " circassian": false, "cambodia": false, "palestinian": false, "iran": false, " arabic": false, "moroccan": false, "tibetan": false, " maay": false, " hindi": false, "arabic": false, "pakistani": false, "palestine": false, " zazaki": false, "tunisian": false, "sinhala": false, "persian": false, "algerian": false, " baraawe": false, "syrian": false, " turkiye": false, "sri lankan": false, " pashto": false, " uzbek": false, "tunisian arabic": false, "khmer": false, " tamil": false, " farsi": false, "urdu": false, " spanish": false, " french": false, "afghanistan": false, " turkish": false, " croatian": false, " tamazight": false, "syria": false, "indian hindhu": false, "bangladesh": false, " balochi": false, "algeria": false, "morocco": false, "cambodian": false, "iranian": false}, "843182197RR0001": {" bosniaks": false, " panjabi": false, "tibet": false, "pakistan": false, "lebanon": false, "bangla": false, "egyptian": false, " pashayi": false, "somalia": false, "egypt": false, " palestinina arabic": false, "sri lanka": false, "hindi": false, "uyghur": false, "gujarati": false, " kurdish": false, " berber": false, "hebrew": false, " chiminii": false, "turkish": false, "tunisia": false, " turkmen": false, "dari": false, " helabasa": false, "jewish": false, "afghan": false, "somali": false, "turkey": false, "lebanese": false, " serbian": false, "turk": false, " armenian": false, "punjabi": false, "bangaldeshi": false, " egyptian arabic": false, "bosnian": false, "israel": false, " lebanese arabic": false, " circassian": false, "cambodia": false, "palestinian": false, "iran": false, " arabic": false, "moroccan": false, "tibetan": false, " maay": false, " hindi": false, "arabic": false, "pakistani": false, "palestine": false, " zazaki": false, "tunisian": false, "sinhala": false, "persian": false, "algerian": false, " baraawe": false, "syrian": false, " turkiye": false, "sri lankan": false, " pashto": false, " uzbek": false, "tunisian arabic": false, "khmer": false, " tamil": false, " farsi": false, "urdu": false, " spanish": false, " french": false, "afghanistan": false, " turkish": false, " croatian": false, " tamazight": false, "syria": false, "indian hindhu": false, "bangladesh": false, " balochi": false, "algeria": false, "morocco": false, "cambodian": false, "iranian": false}}